ps2_census/__init__.py
ps2_census/constants.py
ps2_census/enums.py
ps2_census/event_stream.py
ps2_census/join.py
ps2_census/query.py
ps2_census/tree.py
ps2_census/utils.py
ps2_census-0.13.0.dist-info/LICENSE
ps2_census-0.13.0.dist-info/WHEEL
ps2_census-0.13.0.dist-info/METADATA
ps2_census-0.13.0.dist-info/RECORD
