Metadata-Version: 2.1
Name: ps2-census
Version: 0.13.0
Summary: Daybreak Games Census API client for Planetside 2 (UNOFFICIAL)
Home-page: https://github.com/spascou/ps2-census
License: MIT
Author: Sylvain Pascou
Author-email: sylvain@pascou.net
Requires-Python: >=3.8,<4.0
Classifier: License :: OSI Approved :: MIT License
Classifier: Programming Language :: Python :: 3
Classifier: Programming Language :: Python :: 3.8
Requires-Dist: requests (>=2.23,<3.0)
Requires-Dist: tenacity (>=6.2,<7.0)
Requires-Dist: toml (>=0.9,<0.10)
Requires-Dist: websockets (>=8.1,<9.0)
Project-URL: Repository, https://github.com/spascou/ps2-census
